tooltime/__init__.py
tooltime/exceptions.py
tooltime/py.typed
tooltime/spec.py
tooltime/timefrequency_utils/__init__.py
tooltime/timefrequency_utils/timefrequency_convert.py
tooltime/timefrequency_utils/timefrequency_crud.py
tooltime/timefrequency_utils/timefrequency_identify.py
tooltime/timefrequency_utils/timefrequency_resolution.py
tooltime/timelength_utils/__init__.py
tooltime/timelength_utils/timelength_convert.py
tooltime/timelength_utils/timelength_crud.py
tooltime/timelength_utils/timelength_delta.py
tooltime/timelength_utils/timelength_identify.py
tooltime/timelength_utils/timelength_units.py
tooltime/timeperiod_utils/__init__.py
tooltime/timeperiod_utils/timeperiod_convert.py
tooltime/timeperiod_utils/timeperiod_crud.py
tooltime/timeperiod_utils/timeperiod_df.py
tooltime/timeperiod_utils/timeperiod_identify.py
tooltime/timeperiod_utils/timeperiod_introspect.py
tooltime/timeperiod_utils/timeperiod_overlap.py
tooltime/timeperiod_utils/timeperiod_standard.py
tooltime/timestamp_utils/__init__.py
tooltime/timestamp_utils/datetime_utils.py
tooltime/timestamp_utils/timestamp_convert.py
tooltime/timestamp_utils/timestamp_crud.py
tooltime/timestamp_utils/timestamp_identify.py
tooltime/timestamp_utils/timestamp_introspect.py
tooltime/timestamp_utils/timestamp_samples.py
tooltime-0.3.5.dist-info/licenses/LICENSE
tooltime-0.3.5.dist-info/WHEEL
tooltime-0.3.5.dist-info/METADATA
tooltime-0.3.5.dist-info/RECORD
