Metadata-Version: 2.4
Name: tooltime
Version: 0.3.5
Summary: tooltime makes it easy to create and convert representations of time
Requires-Python: >=3.7
License-File: LICENSE
Requires-Dist: polars>=0.18.4
Requires-Dist: typing-extensions>=4.0.0
Requires-Dist: numpy ; extra == "full"
Requires-Dist: pandas ; extra == "full"
Project-URL: Source, https://github.com/sslivkoff/tooltime
Provides-Extra: full
